showflag/__init__.py
showflag/test.py
showflag-0.1.0.dist-info/METADATA
showflag-0.1.0.dist-info/WHEEL
showflag-0.1.0.dist-info/entry_points.txt
showflag-0.1.0.dist-info/top_level.txt
showflag-0.1.0.dist-info/RECORD
