Metadata-Version: 2.1
Name: showflag
Version: 0.1.0
Summary: A package that prints /flag (for local testing only)
Home-page: UNKNOWN
License: UNKNOWN
Platform: UNKNOWN
Requires-Python: >=3.8
